CHANGES.txt
COPYRIGHT.txt
LICENSE.txt
README.txt
bootstrap.py
buildout.cfg
setup.py
src/zope/__init__.py
src/zope.optionalextension.egg-info/PKG-INFO
src/zope.optionalextension.egg-info/SOURCES.txt
src/zope.optionalextension.egg-info/dependency_links.txt
src/zope.optionalextension.egg-info/top_level.txt
src/zope/optionalextension/build_ext.py
src/zope/optionalextension/tests/__init__.py
src/zope/optionalextension/tests/test_build_ext.py